licence.txt
setup.py
causaln/__init__.py
causaln/calculate_multiple_regression.py
causaln/calculate_write_pairwise_regression.py
causaln/multiple_regression_random_initialisation.py
causaln/network_generator.py
causaln/plot_data.py
causaln/scan_1D_of_network_add_noise.py
causaln.egg-info/PKG-INFO
causaln.egg-info/SOURCES.txt
causaln.egg-info/dependency_links.txt
causaln.egg-info/not-zip-safe
causaln.egg-info/top_level.txt