Metadata-Version: 2.1
Name: causaln
Version: 1.0
Summary: for defining causal networks and generating example data
Home-page: https://github.com/PeterJamesWinn
Author: Peter James Winn
License: MIT
Platform: UNKNOWN
License-File: licence.txt
